{
	"$schema": "http://schema.management.azure.com/schemas/2015-01-01/deploymentTemplate.json#",
	"contentVersion": "1.0.0.0",
	"parameters": {
		"workspaceName": {
			"type": "string",
			"metadata": "Workspace name",
			"defaultValue": "learnsy"
		},
		"AzureBlobStorage1_connectionString": {
			"type": "secureString",
			"metadata": "Secure string for 'connectionString' of 'AzureBlobStorage1'"
		},
		"SqlServer1_connectionString": {
			"type": "secureString",
			"metadata": "Secure string for 'connectionString' of 'SqlServer1'"
		},
		"learnsy-WorkspaceDefaultSqlServer_connectionString": {
			"type": "secureString",
			"metadata": "Secure string for 'connectionString' of 'learnsy-WorkspaceDefaultSqlServer'",
			"defaultValue": "Integrated Security=False;Encrypt=True;Connection Timeout=30;Data Source=tcp:learnsy.sql.azuresynapse.net,1433;Initial Catalog=@{linkedService().DBName}"
		},
		"learnsy-WorkspaceDefaultStorage_properties_typeProperties_url": {
			"type": "string",
			"defaultValue": "https://lakefirst.dfs.core.windows.net"
		}
	},
	"variables": {
		"workspaceId": "[concat('Microsoft.Synapse/workspaces/', parameters('workspaceName'))]"
	},
	"resources": [
		{
			"name": "[concat(parameters('workspaceName'), '/data_to_sql base')]",
			"type": "Microsoft.Synapse/workspaces/pipelines",
			"apiVersion": "2019-06-01-preview",
			"properties": {
				"activities": [
					{
						"name": "data to sql database",
						"type": "Copy",
						"dependsOn": [],
						"policy": {
							"timeout": "0.12:00:00",
							"retry": 0,
							"retryIntervalInSeconds": 30,
							"secureOutput": false,
							"secureInput": false
						},
						"userProperties": [],
						"typeProperties": {
							"source": {
								"type": "DelimitedTextSource",
								"storeSettings": {
									"type": "AzureBlobStorageReadSettings",
									"recursive": true,
									"enablePartitionDiscovery": false
								},
								"formatSettings": {
									"type": "DelimitedTextReadSettings"
								}
							},
							"sink": {
								"type": "SqlServerSink",
								"writeBehavior": "insert",
								"sqlWriterUseTableLock": false
							},
							"enableStaging": false,
							"translator": {
								"type": "TabularTranslator",
								"typeConversion": true,
								"typeConversionSettings": {
									"allowDataTruncation": true,
									"treatBooleanAsNumber": false
								}
							}
						},
						"inputs": [
							{
								"referenceName": "DelimitedText1",
								"type": "DatasetReference",
								"parameters": {}
							}
						],
						"outputs": [
							{
								"referenceName": "SqlServerTable1",
								"type": "DatasetReference",
								"parameters": {}
							}
						]
					}
				],
				"policy": {
					"elapsedTimeMetric": {},
					"cancelAfter": {}
				},
				"annotations": [],
				"lastPublishTime": "2023-08-10T10:12:21Z"
			},
			"dependsOn": [
				"[concat(variables('workspaceId'), '/datasets/DelimitedText1')]",
				"[concat(variables('workspaceId'), '/datasets/SqlServerTable1')]"
			]
		},
		{
			"name": "[concat(parameters('workspaceName'), '/final')]",
			"type": "Microsoft.Synapse/workspaces/pipelines",
			"apiVersion": "2019-06-01-preview",
			"properties": {
				"activities": [
					{
						"name": "Execute Pipeline1",
						"type": "ExecutePipeline",
						"dependsOn": [],
						"userProperties": [],
						"typeProperties": {
							"pipeline": {
								"referenceName": "data_to_sql base",
								"type": "PipelineReference"
							},
							"waitOnCompletion": true,
							"parameters": {}
						}
					},
					{
						"name": "Execute Pipeline2",
						"type": "ExecutePipeline",
						"dependsOn": [
							{
								"activity": "Execute Pipeline1",
								"dependencyConditions": [
									"Completed"
								]
							}
						],
						"userProperties": [],
						"typeProperties": {
							"pipeline": {
								"referenceName": "product_to_cleaning",
								"type": "PipelineReference"
							},
							"waitOnCompletion": true,
							"parameters": {}
						}
					}
				],
				"policy": {
					"elapsedTimeMetric": {},
					"cancelAfter": {}
				},
				"annotations": [],
				"lastPublishTime": "2023-08-10T10:16:37Z"
			},
			"dependsOn": [
				"[concat(variables('workspaceId'), '/pipelines/data_to_sql base')]",
				"[concat(variables('workspaceId'), '/pipelines/product_to_cleaning')]"
			]
		},
		{
			"name": "[concat(parameters('workspaceName'), '/product_to_cleaning')]",
			"type": "Microsoft.Synapse/workspaces/pipelines",
			"apiVersion": "2019-06-01-preview",
			"properties": {
				"activities": [
					{
						"name": "Stored procedure1",
						"type": "SqlServerStoredProcedure",
						"dependsOn": [],
						"policy": {
							"timeout": "0.12:00:00",
							"retry": 0,
							"retryIntervalInSeconds": 30,
							"secureOutput": false,
							"secureInput": false
						},
						"userProperties": [],
						"typeProperties": {
							"storedProcedureName": "[dbo].[Cleaning_data]"
						},
						"linkedServiceName": {
							"referenceName": "SqlServer1",
							"type": "LinkedServiceReference"
						}
					}
				],
				"policy": {
					"elapsedTimeMetric": {},
					"cancelAfter": {}
				},
				"annotations": [],
				"lastPublishTime": "2023-08-10T10:12:15Z"
			},
			"dependsOn": [
				"[concat(variables('workspaceId'), '/linkedServices/SqlServer1')]"
			]
		},
		{
			"name": "[concat(parameters('workspaceName'), '/DelimitedText1')]",
			"type": "Microsoft.Synapse/workspaces/datasets",
			"apiVersion": "2019-06-01-preview",
			"properties": {
				"linkedServiceName": {
					"referenceName": "AzureBlobStorage1",
					"type": "LinkedServiceReference"
				},
				"annotations": [],
				"type": "DelimitedText",
				"typeProperties": {
					"location": {
						"type": "AzureBlobStorageLocation",
						"fileName": "Product_Mapping_spec.csv",
						"container": "data"
					},
					"columnDelimiter": ",",
					"escapeChar": "\\",
					"firstRowAsHeader": true,
					"quoteChar": "\""
				},
				"schema": [
					{
						"name": "ProductID",
						"type": "String"
					},
					{
						"name": "Date",
						"type": "String"
					},
					{
						"name": "CustomerID",
						"type": "String"
					},
					{
						"name": "Units_sold",
						"type": "String"
					},
					{
						"name": "Units",
						"type": "String"
					},
					{
						"name": "Product",
						"type": "String"
					},
					{
						"name": "Category",
						"type": "String"
					},
					{
						"name": "Segment",
						"type": "String"
					},
					{
						"name": "ManufacturerID",
						"type": "String"
					},
					{
						"name": "Manufacturer",
						"type": "String"
					},
					{
						"name": "Unit Cost",
						"type": "String"
					},
					{
						"name": "Unit Price",
						"type": "String"
					},
					{
						"name": "ZipCode",
						"type": "String"
					},
					{
						"name": "Email Name",
						"type": "String"
					},
					{
						"name": "City",
						"type": "String"
					},
					{
						"name": "Region",
						"type": "String"
					},
					{
						"name": "District",
						"type": "String"
					}
				]
			},
			"dependsOn": [
				"[concat(variables('workspaceId'), '/linkedServices/AzureBlobStorage1')]"
			]
		},
		{
			"name": "[concat(parameters('workspaceName'), '/SqlServerTable1')]",
			"type": "Microsoft.Synapse/workspaces/datasets",
			"apiVersion": "2019-06-01-preview",
			"properties": {
				"linkedServiceName": {
					"referenceName": "SqlServer1",
					"type": "LinkedServiceReference"
				},
				"annotations": [],
				"type": "SqlServerTable",
				"schema": [
					{
						"name": "ProductID",
						"type": "varchar"
					},
					{
						"name": "Date",
						"type": "varchar"
					},
					{
						"name": "CustomerID",
						"type": "varchar"
					},
					{
						"name": "units_sold",
						"type": "varchar"
					},
					{
						"name": "Units",
						"type": "varchar"
					},
					{
						"name": "Product",
						"type": "varchar"
					},
					{
						"name": "Category",
						"type": "varchar"
					},
					{
						"name": "Segment",
						"type": "varchar"
					},
					{
						"name": "ManufacturerID",
						"type": "varchar"
					},
					{
						"name": "Manufacturer",
						"type": "varchar"
					},
					{
						"name": "Unit_Cost",
						"type": "varchar"
					},
					{
						"name": "Unit_Price",
						"type": "varchar"
					},
					{
						"name": "ZipCode",
						"type": "varchar"
					},
					{
						"name": "Email_Name",
						"type": "varchar"
					},
					{
						"name": "City",
						"type": "varchar"
					},
					{
						"name": "Region",
						"type": "varchar"
					},
					{
						"name": "District",
						"type": "varchar"
					}
				],
				"typeProperties": {
					"schema": "Products",
					"table": "Product_Staging"
				}
			},
			"dependsOn": [
				"[concat(variables('workspaceId'), '/linkedServices/SqlServer1')]"
			]
		},
		{
			"name": "[concat(parameters('workspaceName'), '/AzureBlobStorage1')]",
			"type": "Microsoft.Synapse/workspaces/linkedServices",
			"apiVersion": "2019-06-01-preview",
			"properties": {
				"annotations": [],
				"type": "AzureBlobStorage",
				"typeProperties": {
					"connectionString": "[parameters('AzureBlobStorage1_connectionString')]"
				},
				"connectVia": {
					"referenceName": "AutoResolveIntegrationRuntime",
					"type": "IntegrationRuntimeReference"
				}
			},
			"dependsOn": [
				"[concat(variables('workspaceId'), '/integrationRuntimes/AutoResolveIntegrationRuntime')]"
			]
		},
		{
			"name": "[concat(parameters('workspaceName'), '/SqlServer1')]",
			"type": "Microsoft.Synapse/workspaces/linkedServices",
			"apiVersion": "2019-06-01-preview",
			"properties": {
				"annotations": [],
				"type": "SqlServer",
				"typeProperties": {
					"connectionString": "[parameters('SqlServer1_connectionString')]"
				},
				"connectVia": {
					"referenceName": "AutoResolveIntegrationRuntime",
					"type": "IntegrationRuntimeReference"
				}
			},
			"dependsOn": [
				"[concat(variables('workspaceId'), '/integrationRuntimes/AutoResolveIntegrationRuntime')]"
			]
		},
		{
			"name": "[concat(parameters('workspaceName'), '/learnsy-WorkspaceDefaultSqlServer')]",
			"type": "Microsoft.Synapse/workspaces/linkedServices",
			"apiVersion": "2019-06-01-preview",
			"properties": {
				"parameters": {
					"DBName": {
						"type": "String"
					}
				},
				"annotations": [],
				"type": "AzureSqlDW",
				"typeProperties": {
					"connectionString": "[parameters('learnsy-WorkspaceDefaultSqlServer_connectionString')]"
				},
				"connectVia": {
					"referenceName": "AutoResolveIntegrationRuntime",
					"type": "IntegrationRuntimeReference"
				}
			},
			"dependsOn": [
				"[concat(variables('workspaceId'), '/integrationRuntimes/AutoResolveIntegrationRuntime')]"
			]
		},
		{
			"name": "[concat(parameters('workspaceName'), '/learnsy-WorkspaceDefaultStorage')]",
			"type": "Microsoft.Synapse/workspaces/linkedServices",
			"apiVersion": "2019-06-01-preview",
			"properties": {
				"annotations": [],
				"type": "AzureBlobFS",
				"typeProperties": {
					"url": "[parameters('learnsy-WorkspaceDefaultStorage_properties_typeProperties_url')]"
				},
				"connectVia": {
					"referenceName": "AutoResolveIntegrationRuntime",
					"type": "IntegrationRuntimeReference"
				}
			},
			"dependsOn": [
				"[concat(variables('workspaceId'), '/integrationRuntimes/AutoResolveIntegrationRuntime')]"
			]
		},
		{
			"name": "[concat(parameters('workspaceName'), '/AutoResolveIntegrationRuntime')]",
			"type": "Microsoft.Synapse/workspaces/integrationRuntimes",
			"apiVersion": "2019-06-01-preview",
			"properties": {
				"type": "Managed",
				"typeProperties": {
					"computeProperties": {
						"location": "AutoResolve",
						"dataFlowProperties": {
							"computeType": "General",
							"coreCount": 8,
							"timeToLive": 0
						}
					}
				}
			},
			"dependsOn": []
		},
		{
			"name": "[concat(parameters('workspaceName'), '/WorkspaceSystemIdentity')]",
			"type": "Microsoft.Synapse/workspaces/credentials",
			"apiVersion": "2019-06-01-preview",
			"properties": {
				"type": "ManagedIdentity",
				"typeProperties": {}
			},
			"dependsOn": []
		},
		{
			"name": "[concat(parameters('workspaceName'), '/SQL script 1')]",
			"type": "Microsoft.Synapse/workspaces/sqlscripts",
			"apiVersion": "2019-06-01-preview",
			"properties": {
				"content": {
					"query": "CREATE PROC products\nAS\nBEGIN\n\t-- Variable declaration\n\tDECLARE @start_time DATETIME,\n\t\t@end_time DATETIME,\n\t\t@source_row_count INT,\n\t\t@target_row_count INT,\n\t\t@error_message VARCHAR(MAX),\n\t\t@ProductID VARCHAR(10),\n\t\t@unit_sold DECIMAL(5),\n\t\t@Product VARCHAR(30),\n\t\t@Total_UnitCost DECIMAL(8,2),\n\t\t@Total_UnitPrice DECIMAL(8,2),\n\t\t@city VARCHAR(30),\n\t\t@maxPurchase DECIMAL(8,2),\n\t\t@profit_percentage INT,\n\t\t@loss_percentage INT\n\t\t\nEND;",
					"metadata": {
						"language": "sql"
					},
					"currentConnection": {
						"databaseName": "sql",
						"poolName": "Built-in"
					},
					"resultLimit": -1
				},
				"type": "SqlQuery"
			},
			"dependsOn": []
		}
	]
}